elabforms/__init__.py
elabforms/cli.py
elabforms/generate_templates.py
elabforms/template.py
elabforms/template_builder.py
elabforms/template_part.py
tests/__init__.py
tests/test_template.py
tests/test_template_builder.py
tests/test_template_part.py
elabforms-0.1.dist-info/METADATA
elabforms-0.1.dist-info/WHEEL
elabforms-0.1.dist-info/entry_points.txt
elabforms-0.1.dist-info/top_level.txt
elabforms-0.1.dist-info/RECORD
