Metadata-Version: 2.4
Name: elabforms
Version: 0.1
Summary: A set of tools to create and manage standardized forms for eLabFTW
Author: Fatai Idrissou, Sylvain Takerkart
License: MIT
Requires-Python: >=3.8
Requires-Dist: gitpython
Requires-Dist: PyYAML~=6.0.1
Requires-Dist: setuptools~=68.2.0
Provides-Extra: test
Requires-Dist: pytest; extra == "test"
Requires-Dist: flake8; extra == "test"
Dynamic: author
Dynamic: description
Dynamic: description-content-type
Dynamic: license
Dynamic: provides-extra
Dynamic: requires-dist
Dynamic: requires-python
Dynamic: summary
